[
  {
    "id": 1,
    "title": "Sci-Fi Blockbuster",
    "releaseDate": "March 15, 2025",
    "poster": "/assets/upcomingEvents/scifi.jpg",
    "showtimes": [
      "12:00 PM",
      "3:00 PM",
      "7:00 PM"
    ],
    "seats": [
      "A1",
      "A2",
      "A3",
      "A4",
      "B1",
      "B2",
      "B3",
      "B4"
    ]
  },
  {
    "id": 2,
    "title": "Romantic Comedy",
    "releaseDate": "April 5, 2025",
    "poster": "/assets/upcomingEvents/scifi.jpg",
    "showtimes": [
      "1:00 PM",
      "4:00 PM",
      "8:00 PM"
    ],
    "seats": [
      "C1",
      "C2",
      "C3",
      "C4",
      "D1",
      "D2",
      "D3",
      "D4"
    ]
  },
  {
    "id": 3,
    "title": "Action Thriller",
    "releaseDate": "May 5, 2025",
    "poster": "/assets/upcomingEvents/scifi.jpg",
    "showtimes": [
      "1:00 PM",
      "4:00 PM",
      "8:00 PM"
    ],
    "seats": [
      "C1",
      "C2",
      "C3",
      "C4",
      "D1",
      "D2",
      "D3",
      "D4"
    ]
  },
  {
    "id": 4,
    "title": "Sci-Fi Blockbuster",
    "releaseDate": "May 5, 2025",
    "poster": "/assets/upcomingEvents/scifi.jpg",
    "showtimes": [
      "1:00 PM",
      "4:00 PM",
      "8:00 PM"
    ],
    "seats": [
      "C1",
      "C2",
      "C3",
      "C4",
      "D1",
      "D2",
      "D3",
      "D4"
    ]
  },
  {
    "id": 5,
    "title": "Romantic Comedy",
    "releaseDate": "May 5, 2025",
    "poster": "/assets/upcomingEvents/scifi.jpg",
    "showtimes": [
      "1:00 PM",
      "4:00 PM",
      "8:00 PM"
    ],
    "seats": [
      "C1",
      "C2",
      "C3",
      "C4",
      "D1",
      "D2",
      "D3",
      "D4"
    ]
  },
  {
    "id": 6,
    "title": "Action Thriller",
    "releaseDate": "May 5, 2025",
    "poster": "/assets/upcomingEvents/scifi.jpg",
    "showtimes": [
      "1:00 PM",
      "4:00 PM",
      "8:00 PM"
    ],
    "seats": [
      "C1",
      "C2",
      "C3",
      "C4",
      "D1",
      "D2",
      "D3",
      "D4"
    ]
  }
]